karrio/mappers/allied_express_local/__init__.py
karrio/mappers/allied_express_local/mapper.py
karrio/mappers/allied_express_local/proxy.py
karrio/mappers/allied_express_local/settings.py
karrio/plugins/allied_express_local/__init__.py
karrio/providers/allied_express_local/__init__.py
karrio/providers/allied_express_local/error.py
karrio/providers/allied_express_local/rate.py
karrio/providers/allied_express_local/tracking.py
karrio/providers/allied_express_local/units.py
karrio/providers/allied_express_local/utils.py
karrio/providers/allied_express_local/shipment/__init__.py
karrio/providers/allied_express_local/shipment/cancel.py
karrio/providers/allied_express_local/shipment/create.py
karrio/schemas/allied_express_local/__init__.py
karrio/schemas/allied_express_local/label_request.py
karrio/schemas/allied_express_local/label_response.py
karrio/schemas/allied_express_local/rate_request.py
karrio/schemas/allied_express_local/rate_response.py
karrio/schemas/allied_express_local/tracking_request.py
karrio/schemas/allied_express_local/tracking_response.py
karrio/schemas/allied_express_local/void_request.py
karrio/schemas/allied_express_local/void_response.py
karrio_allied_express_local-2026.1.4.dist-info/METADATA
karrio_allied_express_local-2026.1.4.dist-info/WHEEL
karrio_allied_express_local-2026.1.4.dist-info/entry_points.txt
karrio_allied_express_local-2026.1.4.dist-info/top_level.txt
karrio_allied_express_local-2026.1.4.dist-info/RECORD
